pyhof/__init__.py
pyhof-0.1.4.dist-info/LICENSE
pyhof-0.1.4.dist-info/WHEEL
pyhof-0.1.4.dist-info/METADATA
pyhof-0.1.4.dist-info/RECORD
